hovertools/__init__.py
hovertools/command_line.py
hovertools/utils.py
hovertools/actions/__init__.py
hovertools/actions/refresh_action.py
hovertools/actions/register_action.py
hovertools/managers/__init__.py
hovertools/managers/docker_manager.py
hovertools-0.1.6.dist-info/DESCRIPTION.rst
hovertools-0.1.6.dist-info/METADATA
hovertools-0.1.6.dist-info/RECORD
hovertools-0.1.6.dist-info/WHEEL
hovertools-0.1.6.dist-info/entry_points.txt
hovertools-0.1.6.dist-info/metadata.json
hovertools-0.1.6.dist-info/top_level.txt
